python_logging_filters/__init__.py
python_logging_filters-0.1.8.dist-info/licenses/LICENSE
python_logging_filters-0.1.8.dist-info/METADATA
python_logging_filters-0.1.8.dist-info/WHEEL
python_logging_filters-0.1.8.dist-info/top_level.txt
python_logging_filters-0.1.8.dist-info/zip-safe
python_logging_filters-0.1.8.dist-info/RECORD
