Metadata-Version: 2.4
Name: python-logging-filters
Version: 0.1.8
Summary: standard python logging filters
Home-page: https://github.com/puzzleYOU/python-logging-filters/
Author: puzzleYOU GmbH
License: MIT
Platform: any
License-File: LICENSE
Dynamic: author
Dynamic: description
Dynamic: description-content-type
Dynamic: home-page
Dynamic: license
Dynamic: license-file
Dynamic: platform
Dynamic: summary
